{
  "name": "NVIDIA GB200 (Single Package)",
  "description": "Single GB200 package with 2 Blackwell GPUs + 1 Grace CPU. Specifications per package.",
  "manufacturer": "NVIDIA",
  "compute_per_package_PFlops": {
    "bf16": 2.5,
    "nvfp8": 5.0,
    "nvfp4": 10.0,
    "int8": 5.0
  },
  "memory_per_package": [
    {"type": "HBM", "capacity_GB": 192.0, "bandwidth_GBs": 8192.0}
  ],
  "interconnect_bandwidth_GBs": 900.0,
  "interconnect_latency_us": 0.20,
  "decode_load_overlap": false,
  "decode_comms_overlap": false,
  "fixed_overhead_per_kernel_us": 100.0,
  "power_kw": 1.0,
  "tco_sec_usd": 0.0015,
  "packages_per_domain": 1,
  "domains_per_cluster": 1
}

